fivetran_provider/__init__.py
fivetran_provider/example_dags/__init__.py
fivetran_provider/example_dags/example_fivetran.py
fivetran_provider/hooks/__init__.py
fivetran_provider/hooks/fivetran.py
fivetran_provider/operators/__init__.py
fivetran_provider/operators/fivetran.py
fivetran_provider/sensors/__init__.py
fivetran_provider/sensors/fivetran.py
airflow_provider_fivetran_atlassian-1.0.0.dist-info/METADATA
airflow_provider_fivetran_atlassian-1.0.0.dist-info/WHEEL
airflow_provider_fivetran_atlassian-1.0.0.dist-info/entry_points.txt
airflow_provider_fivetran_atlassian-1.0.0.dist-info/top_level.txt
airflow_provider_fivetran_atlassian-1.0.0.dist-info/RECORD
